ablil/__init__.py
ablil/bar.py
ablil/fizzbugzz.py
ablil/foo.py
ablil/welcome.py
ablil-1.2.0.dist-info/METADATA
ablil-1.2.0.dist-info/WHEEL
ablil-1.2.0.dist-info/RECORD
