Metadata-Version: 2.3
Name: ablil
Version: 1.2.0
Summary: Python package starter with Poetry
Author: ablil
Author-email: ablil@protonmail.com
Requires-Python: >=3.12,<4.0
Classifier: Programming Language :: Python :: 3
Classifier: Programming Language :: Python :: 3.12
Classifier: Programming Language :: Python :: 3.13
Requires-Dist: requests (>=2.32.3,<3.0.0)
